jax_triton/__init__.py
jax_triton/triton_lib.py
jax_triton/utils.py
jax_triton/version.py
jax_triton/experimental/fusion/__init__.py
jax_triton/experimental/fusion/fusion.py
jax_triton/experimental/fusion/jaxpr_rewriter.py
jax_triton/experimental/fusion/lowering.py
jax_triton-0.3.0.dist-info/licenses/LICENSE
jax_triton-0.3.0.dist-info/METADATA
jax_triton-0.3.0.dist-info/WHEEL
jax_triton-0.3.0.dist-info/top_level.txt
jax_triton-0.3.0.dist-info/RECORD
