Metadata-Version: 2.4
Name: jax-triton
Version: 0.3.0
Summary: JAX + OpenAI Triton integration
Requires-Python: >=3.10
License-File: LICENSE
Requires-Dist: absl-py>=1.4.0
Requires-Dist: jax>=0.6.0
Requires-Dist: triton>=3.3
Provides-Extra: tests
Requires-Dist: pytest; extra == "tests"
Dynamic: license-file
